wx_payautogui/__init__.py
wx_payautogui/core/__init__.py
wx_payautogui/core/bot.py
wx_payautogui/exceptions/__init__.py
wx_payautogui/exceptions/exceptions.py
wx_payautogui/utils/__init__.py
wx_payautogui/utils/image_utils.py
wx_payautogui/utils/logger.py
wx_payautogui/wx_payautogui/__init__.py
wx_payautogui-0.1.0.dist-info/LICENSE
wx_payautogui-0.1.0.dist-info/METADATA
wx_payautogui-0.1.0.dist-info/WHEEL
wx_payautogui-0.1.0.dist-info/top_level.txt
wx_payautogui-0.1.0.dist-info/RECORD
