Metadata-Version: 2.1
Name: wx-payautogui
Version: 0.1.0
Summary: A WeChat automation tool based on pyautogui
Home-page: https://github.com/xiaofang142/wx-payautogui
Author: xiaofang142
Author-email: myloveisphp@163.com
Classifier: Programming Language :: Python :: 3
Classifier: License :: OSI Approved :: MIT License
Classifier: Operating System :: OS Independent
Requires-Python: >=3.7
License-File: LICENSE
Requires-Dist: pyautogui>=0.9.53
Requires-Dist: pillow>=8.0.0
Requires-Dist: opencv-python>=4.5.0
